[
    {
        "city": "Santo Antônio do Sudoeste",
        "state": "PR",
        "district": "Centro",
        "street": "Avenida Brasil 882",
        "zipcode": "85710-970"
    },
    {
        "city": "Santo Antônio do Sudoeste",
        "state": "PR",
        "district": "",
        "street": "",
        "zipcode": "85710-000"
    },
    {
        "city": "Santo Antônio do Sudoeste",
        "state": "PR",
        "district": "Centro",
        "street": "Rua Pedro Balestrim",
        "zipcode": "85725-970"
    }
]