[
    {
        "city": "Jaú do Tocantins",
        "state": "TO",
        "district": "Setor Central",
        "street": "Avenida C 596",
        "zipcode": "77450-970"
    },
    {
        "city": "Jaú do Tocantins",
        "state": "TO",
        "district": "",
        "street": "",
        "zipcode": "77450-000"
    },
    {
        "city": "Jaú do Tocantins",
        "state": "TO",
        "district": "Setor Central",
        "street": "Avenida Principal",
        "zipcode": "77450-971"
    }
]