[
    {
        "city": "Bom Jesus do Galho",
        "state": "MG",
        "district": "Revés do Belém",
        "street": "Rua Castanheira 45",
        "zipcode": "35340-972"
    },
    {
        "city": "Bom Jesus do Galho",
        "state": "MG",
        "district": "Iguaçu",
        "street": "Rua Manoel dos Santos Martins s/n",
        "zipcode": "35340-971"
    },
    {
        "city": "Bom Jesus do Galho",
        "state": "MG",
        "district": "Centro",
        "street": "Rua Vital Martins Bueno 22",
        "zipcode": "35340-970"
    },
    {
        "city": "Bom Jesus do Galho",
        "state": "MG",
        "district": "",
        "street": "",
        "zipcode": "35340-000"
    },
    {
        "city": "Bom Jesus do Galho",
        "state": "MG",
        "district": "São Geraldo",
        "street": "Praça Raimundo Silvério s/n",
        "zipcode": "35340-973"
    }
]