[
    {
        "city": "Posse",
        "state": "GO",
        "district": "Nova Vista",
        "street": "Fazenda Formiga s/n",
        "zipcode": "73900-971"
    },
    {
        "city": "Posse",
        "state": "GO",
        "district": "Centro",
        "street": "Rua Arquimedes Vieira de Brito 179 2ยบ Setor Quadra 5 Lote 1",
        "zipcode": "73900-970"
    },
    {
        "city": "Posse",
        "state": "GO",
        "district": "",
        "street": "",
        "zipcode": "73900-000"
    }
]